MANIFEST.in
README.md
setup.py
avmu/__init__.py
avmu/__main__.py
avmu/avmu_exceptions.py
avmu/avmu_library.py
avmu/avmu_utils.py
avmu/avmudll_amd64_win.dll
avmu/combo_utils.py
avmu/dll_loader.py
avmu/load_header.py
avmu.egg-info/PKG-INFO
avmu.egg-info/SOURCES.txt
avmu.egg-info/dependency_links.txt
avmu.egg-info/requires.txt
avmu.egg-info/top_level.txt
avmu/headers/avmu_header_agg.h
avmu/headers/avmu_header_agg_c.h
avmu/headers/vna_header_agg_c.h