Metadata-Version: 2.1
Name: avmu
Version: 0.1.1
Summary: Control interface and API for running Akela Vector Measurement Units.
Home-page: https://github.com/AkelaInc/avmu
Author: Connor Wolf, Akela Inc
Author-email: cwolf@akelainc.com
License: UNKNOWN
Platform: UNKNOWN
Classifier: Programming Language :: Python :: 3
Classifier: Development Status :: 3 - Alpha
Classifier: Intended Audience :: Science/Research
Classifier: Operating System :: Microsoft :: Windows
Requires-Python: >=3.4
